.travis.yml
README.rst
bootstrap.py
buildout.cfg
setup.py
docs/CHANGES.txt
docs/conf.py
docs/index.rst
zyklop/__init__.py
zyklop/command.py
zyklop/search.py
zyklop/ssh.py
zyklop.egg-info/PKG-INFO
zyklop.egg-info/SOURCES.txt
zyklop.egg-info/dependency_links.txt
zyklop.egg-info/entry_points.txt
zyklop.egg-info/not-zip-safe
zyklop.egg-info/requires.txt
zyklop.egg-info/top_level.txt
zyklop/tests/__init__.py
zyklop/tests/base.py
zyklop/tests/test_search.py
zyklop/tests/test_ssh.py
zyklop/tests/test_sync.py
zyklop/tests/testdata/samplesshconfig.cfg
zyklop/tests/testdata/dirtree/folder1/bin/instance
zyklop/tests/testdata/dirtree/folder1/etc/file1.txt
zyklop/tests/testdata/dirtree/folder1/etc/file2.txt
zyklop/tests/testdata/dirtree/folder2/file2.txt
zyklop/tests/testdata/dirtree/folder3/python2.6/file2.txt
zyklop/tests/testdata/dirtree/folder3/python2.6/folder1/file2.txt