Metadata-Version: 1.0
Name: zyklop
Version: 0.5.1
Summary: Rsync wrapper making syncing easy
Home-page: http://zyklop.rtfd.org
Author: Róman Joost
Author-email: roman@bromeco.de
License: GPL
Keywords: server
Platform: UNKNOWN
Classifier: Environment :: Console
Classifier: Intended Audience :: Developers
Classifier: License :: OSI Approved :: GNU General Public License (GPL)
Classifier: Programming Language :: Python
Classifier: Topic :: Internet
Classifier: Topic :: Software Development :: Libraries :: Python Modules
Classifier: Topic :: System :: Archiving :: Backup
Classifier: Topic :: System :: Archiving :: Mirroring
Classifier: Topic :: System :: Systems Administration
